mcp_portfolio_server/__init__.py
mcp_portfolio_server/server.py
srikanth_mcp_portfolio-1.5.0.data/data/share/srikanth-mcp-portfolio/db/sample-data.json
srikanth_mcp_portfolio-1.5.0.dist-info/METADATA
srikanth_mcp_portfolio-1.5.0.dist-info/WHEEL
srikanth_mcp_portfolio-1.5.0.dist-info/entry_points.txt
srikanth_mcp_portfolio-1.5.0.dist-info/RECORD
