Metadata-Version: 2.4
Name: srikanth-mcp-portfolio
Version: 1.5.0
Summary: MCP server for Srikanth's portfolio data
Project-URL: Homepage, https://github.com/srikanthkarthi/mcp-portfolio
Project-URL: Repository, https://github.com/srikanthkarthi/mcp-portfolio
Project-URL: Documentation, https://github.com/srikanthkarthi/mcp-portfolio#readme
Author-email: Srikanth Karthikeyan <srikanthkarthi2003@gmail.com>
License: MIT
Keywords: data,mcp,portfolio,server
Classifier: Development Status :: 4 - Beta
Classifier: Intended Audience :: Developers
Classifier: License :: OSI Approved :: MIT License
Classifier: Programming Language :: Python :: 3
Classifier: Programming Language :: Python :: 3.8
Classifier: Programming Language :: Python :: 3.9
Classifier: Programming Language :: Python :: 3.10
Classifier: Programming Language :: Python :: 3.11
Classifier: Programming Language :: Python :: 3.12
Requires-Python: >=3.8
Requires-Dist: mcp>=1.0.0
